fauna_api/__init__.py
fauna_api/application.py
fauna_api/client.py
fauna_api/decorators.py
fauna_api/json.py
fauna_api/lib/__init__.py
fauna_api/lib/errors.py
fauna_api/lib/objects.py
fauna_api/lib/page.py
fauna_api/lib/query.py
fauna_api/odm.py
fauna_api/streams.py
fauna_api/typedefs.py
fauna_api/utils.py
fauna_api-0.0.3.dist-info/METADATA
fauna_api-0.0.3.dist-info/WHEEL
fauna_api-0.0.3.dist-info/RECORD
