Metadata-Version: 2.1
Name: fauna-api
Version: 0.0.3
Summary: 
Author: Oscar Bahamonde
Author-email: oscar.bahamonde@aiofauna.com
Requires-Python: >=3.8,<4.0
Classifier: Programming Language :: Python :: 3
Classifier: Programming Language :: Python :: 3.8
Classifier: Programming Language :: Python :: 3.9
Classifier: Programming Language :: Python :: 3.10
Classifier: Programming Language :: Python :: 3.11
Requires-Dist: fastapi (>=0.103.0,<0.104.0)
Requires-Dist: httpx[http2] (>=0.24.1,<0.25.0)
Requires-Dist: iso8601 (>=2.0.0,<3.0.0)
Requires-Dist: mangum (>=0.17.0,<0.18.0)
Requires-Dist: markdown-it-py[linkify] (>=3.0.0,<4.0.0)
Requires-Dist: pydantic (==1.10.12)
Requires-Dist: rich (>=13.5.2,<14.0.0)
